MANIFEST.in
README.md
setup.cfg
setup.py
interaction_aware_motion_prediction/__init__.py
interaction_aware_motion_prediction/observation.py
interaction_aware_motion_prediction/planner.py
interaction_aware_motion_prediction/planner_utils.py
interaction_aware_motion_prediction/policy.py
interaction_aware_motion_prediction/predictor.py
interaction_aware_motion_prediction/predictor_5000_0.6726.pth
smarts_agent_iamp.egg-info/PKG-INFO
smarts_agent_iamp.egg-info/SOURCES.txt
smarts_agent_iamp.egg-info/dependency_links.txt
smarts_agent_iamp.egg-info/requires.txt
smarts_agent_iamp.egg-info/top_level.txt
smarts_agent_iamp.egg-info/zip-safe